aiger_bdd/__init__.py
aiger_bdd/bdd.py
aiger_bdd/test_bdd.py
py_aiger_bdd-3.1.3.dist-info/LICENSE
py_aiger_bdd-3.1.3.dist-info/METADATA
py_aiger_bdd-3.1.3.dist-info/WHEEL
py_aiger_bdd-3.1.3.dist-info/RECORD
