Metadata-Version: 2.1
Name: py-aiger-bdd
Version: 3.1.3
Summary: Aiger to BDD bridge.
Home-page: https://github.com/mvcisback/py-aiger-bdd
License: MIT
Author: Marcell Vazquez-Chanlatte
Author-email: mvc@linux.com
Requires-Python: >=3.11,<4.0
Classifier: License :: OSI Approved :: MIT License
Classifier: Programming Language :: Python :: 3
Classifier: Programming Language :: Python :: 3.11
Classifier: Programming Language :: Python :: 3.12
Requires-Dist: attrs (>=22)
Requires-Dist: bidict (>=0.22.0,<0.23.0)
Requires-Dist: dd (>=0.6.0,<0.7.0)
Requires-Dist: funcy (>=1.12,<2.0)
Requires-Dist: py-aiger (>=6.0.0,<7.0.0)
Project-URL: Repository, https://github.com/mvcisback/py-aiger-bdd
